[
  {
    "firstname": "Benson",
    "lastname": "Hayes",
    "reactiveProgrammingLevel": 2,
    "hasSpringWebFluxExperience": false
  },
  {
    "firstname": "Theodore",
    "lastname": "Jackson",
    "reactiveProgrammingLevel": 1,
    "hasSpringWebFluxExperience": false
  },
  {
    "firstname": "Lorenzo",
    "lastname": "Morgan",
    "reactiveProgrammingLevel": 2,
    "hasSpringWebFluxExperience": false
  },
  {
    "firstname": "Romeo",
    "lastname": "Edwards",
    "reactiveProgrammingLevel": 1,
    "hasSpringWebFluxExperience": true
  },
  {
    "firstname": "Uriyah",
    "lastname": "Brown",
    "reactiveProgrammingLevel": 1,
    "hasSpringWebFluxExperience": false
  },
  {
    "firstname": "Alan",
    "lastname": "Thomas",
    "reactiveProgrammingLevel": 3,
    "hasSpringWebFluxExperience": true
  },
  {
    "firstname": "Seamus",
    "lastname": "Long",
    "reactiveProgrammingLevel": 1,
    "hasSpringWebFluxExperience": false
  }
]